<?xml version="1.0" encoding="UTF-8"?>
<AcsCommandCenterProject xmlns="Alma/Acs/AcsCommandCenterProject"
    xmlns:xsi="http://www.w3.org/2001/XMLSchema-instance"
    creator="acc-v8.1" xsi:type="AcsCommandCenterProject">
    <mode>local</mode>
    <servicesLocalJavaRoot></servicesLocalJavaRoot>
    <scriptBase>0</scriptBase>
    <remoteHost>192.168.200.200</remoteHost>
    <remoteAccount></remoteAccount>
    <remotePassword></remotePassword>
    <toolRunAgainstDedicatedSettings>false</toolRunAgainstDedicatedSettings>
    <toolAgainstManagerHost></toolAgainstManagerHost>
    <toolAgainstManagerPort></toolAgainstManagerPort>
    <toolAgainstInterfaceRepository></toolAgainstInterfaceRepository>
    <toolAgainstNameService></toolAgainstNameService>
    <containers>
        <select>3</select>
        <againstManagerHost></againstManagerHost>
        <againstManagerPort></againstManagerPort>
        <againstCDB></againstCDB>
        <againstInterfaceRepository></againstInterfaceRepository>
        <container>
            <name>AntennaBossContainer</name>
            <type>cpp</type>
        </container>
        <container>
            <name>AntennaContainer</name>
            <type>cpp</type>
        </container>
        <container>
            <name>CalibrationToolContainer</name>
            <type>cpp</type>
        </container>
        <container>
            <name>ExternalClientsContainer</name>
            <type>cpp</type>
        </container>
        <container>
            <name>FitsZillaContainer</name>
            <type>cpp</type>
        </container>
        <container>
            <name>LoggerContainer</name>
            <type>cpp</type>
        </container>
        <container>
            <name>ManagementContainer</name>
            <type>cpp</type>
        </container>
        <container>
            <name>MinorServoBossContainer</name>
            <type>cpp</type>
        </container>
        <container>
            <name>MinorServoContainer</name>
            <type>cpp</type>
        </container>
        <container>
            <name>MountContainer</name>
            <type>cpp</type>
        </container>
        <container>
            <name>PointContainer</name>
            <type>cpp</type>
        </container>
        <container>
            <name>ReceiversContainer</name>
            <type>cpp</type>
        </container>
        <container>
            <name>SRT7GHzContainer</name>
            <type>cpp</type>
        </container>
        <container>
            <name>SRTKBandContainer</name>
            <type>cpp</type>
        </container>
        <container>
            <name>SRTLPBandContainer</name>
            <type>cpp</type>
        </container>
        <container>
            <name>TotalPowerContainer</name>
            <type>cpp</type>
        </container>
        <container>
            <name>WeatherStationContainer</name>
            <type>cpp</type>
        </container>
        <container>
            <name>XContainer</name>
            <type>cpp</type>
        </container>
    </containers>
</AcsCommandCenterProject>
